augini/__init__.py
augini/config.py
augini/data_analyzer.py
augini/data_engineer.py
augini/exceptions.py
augini/utils.py
augini-0.3.0.dist-info/LICENSE
augini-0.3.0.dist-info/METADATA
augini-0.3.0.dist-info/WHEEL
augini-0.3.0.dist-info/top_level.txt
augini-0.3.0.dist-info/RECORD
