Metadata-Version: 2.2
Name: augini
Version: 0.3.0
Summary: AI-powered Python framework for tabular data enrichment and analysis using LLMs. Features include intelligent feature engineering, natural language data analysis, and AI agents for automated workflows.
Author-email: Vadim Borisov <vadim@tabularis.ai>
License: MIT License
Project-URL: Homepage, https://github.com/tabularis-ai/augini
Project-URL: Bug Tracker, https://github.com/tabularis-ai/augini/issues
Project-URL: Documentation, https://tabularis-ai.github.io/augini
Project-URL: Discord, https://discord.com/channels/1310217643520819251/
Keywords: AI agents,augini,LLM,data analysis,feature engineering,tabular data,data enrichment,natural language,data science,machine learning
Classifier: Development Status :: 3 - Alpha
Classifier: Intended Audience :: Developers
Classifier: Intended Audience :: Science/Research
Classifier: License :: OSI Approved :: MIT License
Classifier: Operating System :: OS Independent
Classifier: Programming Language :: Python :: 3
Classifier: Programming Language :: Python :: 3.7
Classifier: Programming Language :: Python :: 3.8
Classifier: Programming Language :: Python :: 3.9
Classifier: Programming Language :: Python :: 3.10
Classifier: Programming Language :: Python :: 3.11
Classifier: Topic :: Scientific/Engineering :: Artificial Intelligence
Classifier: Topic :: Software Development :: Libraries :: Python Modules
Classifier: Topic :: Scientific/Engineering :: Information Analysis
Requires-Python: >=3.7
License-File: LICENSE
Requires-Dist: openai>=1.35.13
Requires-Dist: pandas>=2.0.0
Requires-Dist: numpy<2.0.0
Requires-Dist: tqdm>=4.65.0
Requires-Dist: nest_asyncio>=1.5.6
Requires-Dist: pydantic>=2.0.0
Requires-Dist: PyYAML>=6.0.0
Requires-Dist: python-dotenv>=1.0.0
Provides-Extra: dev
Requires-Dist: pytest>=7.0.0; extra == "dev"
Requires-Dist: black>=22.0.0; extra == "dev"
Requires-Dist: isort>=5.0.0; extra == "dev"
Requires-Dist: mypy>=1.0.0; extra == "dev"
Requires-Dist: pylint>=2.17.0; extra == "dev"
Requires-Dist: mkdocs-material>=9.0.0; extra == "dev"
Requires-Dist: mkdocs-minify-plugin>=0.7.0; extra == "dev"
